modelstack/__init__.py
modelstack/cli.py
modelstack/db.py
modelstack/utils.py
modelstack-1.0.1.dist-info/LICENSE
modelstack-1.0.1.dist-info/METADATA
modelstack-1.0.1.dist-info/WHEEL
modelstack-1.0.1.dist-info/entry_points.txt
modelstack-1.0.1.dist-info/top_level.txt
modelstack-1.0.1.dist-info/RECORD
