Metadata-Version: 2.1
Name: modelstack
Version: 1.0.1
Summary: ModelStack - Lightweight Local Model Registry
Home-page: https://github.com/Aniruddh-k/modelstack
Author: Aniruddha
Author-email: aniruddhakide16@example.com
Classifier: Programming Language :: Python :: 3
Classifier: License :: OSI Approved :: MIT License
Classifier: Operating System :: OS Independent
Requires-Python: >=3.7
License-File: LICENSE
Requires-Dist: click
Requires-Dist: tabulate
Requires-Dist: joblib
Requires-Dist: torch
Requires-Dist: scikit-learn
Requires-Dist: numpy
